harvest/__init__.py
harvest/credentials.py
harvest/endpoints.py
harvest/services.py
harvest_api-0.4.0.dist-info/LICENSE
harvest_api-0.4.0.dist-info/METADATA
harvest_api-0.4.0.dist-info/WHEEL
harvest_api-0.4.0.dist-info/top_level.txt
harvest_api-0.4.0.dist-info/RECORD
