Metadata-Version: 2.1
Name: harvest-api
Version: 0.4.0
Summary: Harvest API
Home-page: https://github.com/velvetkeyboard/py-harvest-api
Author: Ramon Moraes
Author-email: ramonmoraes8080@gmail.com
License: MIT
Platform: UNKNOWN
Requires-Dist: requests (>=2.19.1)
